wowool/analysis_formatter/analysis_formatter.py
wowool/analysis_formatter/app_id.py
wowool/apps/analysis_formatter/__init__.py
wowool/apps/analysis_formatter/config.py
wowool_analysis_formatter-2.3.1.dist-info/METADATA
wowool_analysis_formatter-2.3.1.dist-info/WHEEL
wowool_analysis_formatter-2.3.1.dist-info/top_level.txt
wowool_analysis_formatter-2.3.1.dist-info/RECORD
