Metadata-Version: 2.4
Name: wowool-analysis-formatter
Version: 2.3.1
Summary: Wowool Analysis Formatter
Home-page: https://www.wowool.com/
Author: Wowool
Author-email: info@wowool.com
Requires-Python: >=3.10
Requires-Dist: wowool-common<4.0,>=3.6
Dynamic: author
Dynamic: author-email
Dynamic: description
Dynamic: description-content-type
Dynamic: home-page
Dynamic: requires-dist
Dynamic: requires-python
Dynamic: summary
